neorl2/__init__.py
neorl2/envs/__init__.py
neorl2/envs/_msd.py
neorl2/envs/base.py
neorl2/envs/dmsd.py
neorl2/envs/fusion.py
neorl2/envs/fusion_toy.py
neorl2/envs/info.py
neorl2/envs/pipline.py
neorl2/envs/randomfrictionhopper.py
neorl2/envs/rocketrecovery.py
neorl2/envs/safetyhalfcheetah.py
neorl2/envs/salespromotion.py
neorl2/envs/simglucose.py
neorl2-0.0.1.dist-info/METADATA
neorl2-0.0.1.dist-info/WHEEL
neorl2-0.0.1.dist-info/top_level.txt
neorl2-0.0.1.dist-info/RECORD
